LICENSE
MANIFEST.in
README.md
README_PYPI.md
pyproject.toml
setup.cfg
setup.py
./Cpywpa/__init__.py
./Cpywpa/ccore/__init__.py
./Cpywpa/ccore/_cpywpa_core.c
./Cpywpa/ccore/cpywpa_error.py
./Cpywpa/ccore/cpywpa_wrapper.py
Cpywpa.egg-info/PKG-INFO
Cpywpa.egg-info/SOURCES.txt
Cpywpa.egg-info/dependency_links.txt
Cpywpa.egg-info/requires.txt
Cpywpa.egg-info/top_level.txt
Cpywpa/ccore/_cpywpa_core.pyx
Cpywpa/ccore/c_cpw_core.c
Cpywpa/ccore/include/build_config.h
Cpywpa/ccore/include/common.c
Cpywpa/ccore/include/common.h
Cpywpa/ccore/include/includes.h
Cpywpa/ccore/include/os.h
Cpywpa/ccore/include/os_unix.c
Cpywpa/ccore/include/wpa_ctrl.c
Cpywpa/ccore/include/wpa_ctrl.h
Cpywpa/ccore/include/wpa_debug.c
Cpywpa/ccore/include/wpa_debug.h
Cpywpa/ccore/include/wpabuf.c
Cpywpa/ccore/include/wpabuf.h