Metadata-Version: 2.1
Name: Cpywpa
Version: 1.0
Summary: Cpywpa is another simple tools to control wpa_supplicant. It use Cython to interact with OFFICIAL C interface
Home-page: UNKNOWN
Author: Syize
Author-email: syizeliu@gmail.com
License: UNKNOWN
Platform: Linux
License-File: LICENSE
